LICENSE
README.md
setup.cfg
setup.py
azuredol/__init__.py
azuredol/_old_base.py
azuredol/base.py
azuredol/functions.py
azuredol.egg-info/PKG-INFO
azuredol.egg-info/SOURCES.txt
azuredol.egg-info/dependency_links.txt
azuredol.egg-info/not-zip-safe
azuredol.egg-info/requires.txt
azuredol.egg-info/top_level.txt