Metadata-Version: 2.1
Name: azuredol
Version: 0.1.7
Summary: Azure Storage Data Object Layer
Home-page: https://github.com/i2mint/azuredol
License: apache-2.0
Keywords: azure,storage,blob
Platform: any
License-File: LICENSE
